cytnx_core/_core.cpython-311-x86_64-linux-gnu.so
cytnx_core/__init__.py
cytnx_core/_core/__init__.pyi
cytnx_core/_core/device/__init__.pyi
cytnx_core/cpp/include/cytnx_core/Type.hpp
cytnx_core/cpp/include/cytnx_core/cytnx_core.hpp
cytnx_core/cpp/include/cytnx_core/lapack_wrapper.hpp
cytnx_core/cpp/include/cytnx_core/Device.hpp
cytnx_core/cpp/include/cytnx_core/errors/cytnx_error.hpp
cytnx_core/cpp/include/cytnx_core/errors/cuda.hpp
cytnx_core/cpp/include/cytnx_core/errors/base.hpp
cytnx_core/cpp/lib/libcytnx_core.a
cytnx_core-0.1.0.dist-info/METADATA
cytnx_core-0.1.0.dist-info/RECORD
cytnx_core-0.1.0.dist-info/WHEEL
