Metadata-Version: 2.1
Name: cytnx-core
Version: 0.1.0
Summary: Core component of cytnx
Author-Email: kaihsin <kaihsinwu@gmail.com>
Requires-Python: >=3.10
Requires-Dist: cibuildwheel>=2.22.0
Requires-Dist: numpy>=2.2.0
Requires-Dist: scipy-openblas64>=0.3.28.0.2
